COPYING
LICENSE
MANIFEST.in
README.rst
distribute_setup.py
rtd-requirements.txt
setup.py
Orange_Reliability.egg-info/PKG-INFO
Orange_Reliability.egg-info/SOURCES.txt
Orange_Reliability.egg-info/dependency_links.txt
Orange_Reliability.egg-info/entry_points.txt
Orange_Reliability.egg-info/not-zip-safe
Orange_Reliability.egg-info/requires.txt
Orange_Reliability.egg-info/top_level.txt
docs/Makefile
docs/rst/Orange.evaluation.reliability.rst
docs/rst/conf.py
docs/rst/index.rst
docs/rst/code/reliability-basic.py
docs/rst/code/reliability-long.py
docs/rst/code/reliability-run.py
orangecontrib/__init__.py
orangecontrib/reliability/__init__.py
orangecontrib/reliability/widgets/OWReliability.py
orangecontrib/reliability/widgets/__init__.py
orangecontrib/reliability/widgets/icons/Reliability.svg