Metadata-Version: 1.1
Name: Orange-Reliability
Version: 0.2.14
Summary: Orange Reliability add-on for Orange data mining software package.
Home-page: http://orange.biolab.si/addons/
Author: Bioinformatics Laboratory, FRI UL
Author-email: contact@orange.biolab.si
License: GPLv3
Download-URL: https://bitbucket.org/biolab/orange-reliability/downloads
Keywords: data mining,machine learning,artificial intelligence,reliability,orange,orange add-on
Platform: UNKNOWN
Classifier: Development Status :: 4 - Beta
Classifier: Environment :: X11 Applications :: Qt
Classifier: Environment :: Console
Classifier: Environment :: Plugins
Classifier: Programming Language :: Python
Classifier: License :: OSI Approved :: GNU General Public License v3 or later (GPLv3+)
Classifier: Operating System :: OS Independent
Classifier: Topic :: Scientific/Engineering :: Artificial Intelligence
Classifier: Topic :: Scientific/Engineering :: Visualization
Classifier: Topic :: Scientific/Engineering :: Bio-Informatics
Classifier: Topic :: Software Development :: Libraries :: Python Modules
Classifier: Intended Audience :: Education
Classifier: Intended Audience :: Science/Research
Classifier: Intended Audience :: Developers
